cf_wrapper/__init__.py
cf_wrapper/cli.py
cf_wrapper/sdk.py
cf_wrapper-0.1.19.dist-info/METADATA
cf_wrapper-0.1.19.dist-info/WHEEL
cf_wrapper-0.1.19.dist-info/entry_points.txt
cf_wrapper-0.1.19.dist-info/top_level.txt
cf_wrapper-0.1.19.dist-info/RECORD
