Metadata-Version: 2.1
Name: cf-wrapper
Version: 0.1.19
Summary: UNKNOWN
Home-page: UNKNOWN
License: UNKNOWN
Platform: UNKNOWN
Requires-Dist: boto3>=1.26.0
Requires-Dist: requests>=2.28.0
Requires-Dist: python-dotenv>=0.19.0
Requires-Dist: click>=8.0.0
